sigdf/Eula.txt
sigdf/README.MD
sigdf/__init__.py
sigdf/requirements.txt
sigdf/sigcheck.exe
sigdf/sigcheck64.exe
sigdf/sigcheck64a.exe
sigdf/thirdparty.json
sigdf-0.10.dist-info/LICENSE.rst
sigdf-0.10.dist-info/METADATA
sigdf-0.10.dist-info/WHEEL
sigdf-0.10.dist-info/top_level.txt
sigdf-0.10.dist-info/RECORD
