Metadata-Version: 2.1
Name: sigdf
Version: 0.10
Summary: provides a convenient and efficient way to retrieve signature information (Microsoft's sigcheck) for files and converts it to a pandas DataFrame
Home-page: https://github.com/hansalemaos/sigdf
Author: Johannes Fischer
Author-email: aulasparticularesdealemaosp@gmail.com
License: MIT
Keywords: microsoft,sigcheck
Classifier: Development Status :: 4 - Beta
Classifier: Programming Language :: Python :: 3 :: Only
Classifier: Programming Language :: Python :: 3.10
Classifier: Topic :: Software Development :: Libraries :: Python Modules
Classifier: Topic :: Utilities
License-File: LICENSE.rst
Requires-Dist: a-pandas-ex-apply-ignore-exceptions
Requires-Dist: a-pandas-ex-less-memory-more-speed
Requires-Dist: getfilenuitkapython
Requires-Dist: list-all-files-recursively
Requires-Dist: pandas
